gossiphs_mcp/__init__.py
gossiphs_mcp/cmd.py
gossiphs_mcp/server.py
gossiphs_mcp/tools.py
gossiphs_mcp-0.1.1.dist-info/METADATA
gossiphs_mcp-0.1.1.dist-info/WHEEL
gossiphs_mcp-0.1.1.dist-info/entry_points.txt
gossiphs_mcp-0.1.1.dist-info/licenses/LICENSE
gossiphs_mcp-0.1.1.dist-info/RECORD
