Metadata-Version: 2.4
Name: gossiphs_mcp
Version: 0.1.1
Summary: gossiphs wrapper for model context protocol
License: Apache License
License-File: LICENSE
Requires-Python: >=3.11
Requires-Dist: fire>=0.7.0
Requires-Dist: gossiphs>=0.11.5
Requires-Dist: mcp[cli]>=1.3.0
